anfrac/__init__.py
anfrac/fraction.py
anfrac-0.1.0.dist-info/LICENSE
anfrac-0.1.0.dist-info/METADATA
anfrac-0.1.0.dist-info/WHEEL
anfrac-0.1.0.dist-info/top_level.txt
anfrac-0.1.0.dist-info/RECORD
